Metadata-Version: 2.1
Name: soda-sql-sqlserver
Version: 2.2.2
Classifier: Development Status :: 4 - Beta
Classifier: License :: OSI Approved :: Apache Software License
Classifier: Operating System :: Microsoft :: Windows
Classifier: Operating System :: MacOS :: MacOS X
Classifier: Operating System :: POSIX :: Linux
Classifier: Programming Language :: Python :: 3.7
Classifier: Programming Language :: Python :: 3.8
Classifier: Programming Language :: Python :: 3.9
Requires-Dist: soda-sql-core (==2.2.2)
Requires-Dist: pyodbc (<5.0,>=4.0.30)
